[
  {
    "supporter_id": "5",
    "display_name": "5",
    "probability": 0.7707,
    "tier": "High Risk"
  },
  {
    "supporter_id": "5",
    "display_name": "5",
    "probability": 0.7512,
    "tier": "High Risk"
  },
  {
    "supporter_id": "46",
    "display_name": "46",
    "probability": 0.741,
    "tier": "High Risk"
  },
  {
    "supporter_id": "15",
    "display_name": "15",
    "probability": 0.7369,
    "tier": "High Risk"
  },
  {
    "supporter_id": "42",
    "display_name": "42",
    "probability": 0.7351,
    "tier": "High Risk"
  },
  {
    "supporter_id": "43",
    "display_name": "43",
    "probability": 0.7338,
    "tier": "High Risk"
  },
  {
    "supporter_id": "46",
    "display_name": "46",
    "probability": 0.7313,
    "tier": "High Risk"
  },
  {
    "supporter_id": "41",
    "display_name": "41",
    "probability": 0.729,
    "tier": "High Risk"
  },
  {
    "supporter_id": "42",
    "display_name": "42",
    "probability": 0.7282,
    "tier": "High Risk"
  },
  {
    "supporter_id": "10",
    "display_name": "10",
    "probability": 0.7132,
    "tier": "High Risk"
  },
  {
    "supporter_id": "41",
    "display_name": "41",
    "probability": 0.7114,
    "tier": "High Risk"
  },
  {
    "supporter_id": "47",
    "display_name": "47",
    "probability": 0.7053,
    "tier": "High Risk"
  },
  {
    "supporter_id": "40",
    "display_name": "40",
    "probability": 0.7011,
    "tier": "High Risk"
  },
  {
    "supporter_id": "15",
    "display_name": "15",
    "probability": 0.6997,
    "tier": "Medium Risk"
  },
  {
    "supporter_id": "44",
    "display_name": "44",
    "probability": 0.6992,
    "tier": "Medium Risk"
  },
  {
    "supporter_id": "40",
    "display_name": "40",
    "probability": 0.6946,
    "tier": "Medium Risk"
  },
  {
    "supporter_id": "13",
    "display_name": "13",
    "probability": 0.6931,
    "tier": "Medium Risk"
  },
  {
    "supporter_id": "21",
    "display_name": "21",
    "probability": 0.6914,
    "tier": "Medium Risk"
  },
  {
    "supporter_id": "9",
    "display_name": "9",
    "probability": 0.6888,
    "tier": "Medium Risk"
  },
  {
    "supporter_id": "43",
    "display_name": "43",
    "probability": 0.6885,
    "tier": "Medium Risk"
  },
  {
    "supporter_id": "59",
    "display_name": "59",
    "probability": 0.6771,
    "tier": "Medium Risk"
  },
  {
    "supporter_id": "50",
    "display_name": "50",
    "probability": 0.6696,
    "tier": "Medium Risk"
  },
  {
    "supporter_id": "22",
    "display_name": "22",
    "probability": 0.6663,
    "tier": "Medium Risk"
  },
  {
    "supporter_id": "48",
    "display_name": "48",
    "probability": 0.6619,
    "tier": "Medium Risk"
  },
  {
    "supporter_id": "24",
    "display_name": "24",
    "probability": 0.6611,
    "tier": "Medium Risk"
  },
  {
    "supporter_id": "23",
    "display_name": "23",
    "probability": 0.6582,
    "tier": "Medium Risk"
  },
  {
    "supporter_id": "56",
    "display_name": "56",
    "probability": 0.6554,
    "tier": "Medium Risk"
  },
  {
    "supporter_id": "55",
    "display_name": "55",
    "probability": 0.6481,
    "tier": "Medium Risk"
  },
  {
    "supporter_id": "11",
    "display_name": "11",
    "probability": 0.6466,
    "tier": "Medium Risk"
  },
  {
    "supporter_id": "30",
    "display_name": "30",
    "probability": 0.6384,
    "tier": "Medium Risk"
  },
  {
    "supporter_id": "19",
    "display_name": "19",
    "probability": 0.637,
    "tier": "Medium Risk"
  },
  {
    "supporter_id": "50",
    "display_name": "50",
    "probability": 0.6368,
    "tier": "Medium Risk"
  },
  {
    "supporter_id": "11",
    "display_name": "11",
    "probability": 0.6367,
    "tier": "Medium Risk"
  },
  {
    "supporter_id": "37",
    "display_name": "37",
    "probability": 0.6364,
    "tier": "Medium Risk"
  },
  {
    "supporter_id": "55",
    "display_name": "55",
    "probability": 0.6364,
    "tier": "Medium Risk"
  },
  {
    "supporter_id": "59",
    "display_name": "59",
    "probability": 0.6361,
    "tier": "Medium Risk"
  },
  {
    "supporter_id": "16",
    "display_name": "16",
    "probability": 0.6319,
    "tier": "Medium Risk"
  },
  {
    "supporter_id": "56",
    "display_name": "56",
    "probability": 0.6305,
    "tier": "Medium Risk"
  },
  {
    "supporter_id": "48",
    "display_name": "48",
    "probability": 0.6281,
    "tier": "Medium Risk"
  },
  {
    "supporter_id": "59",
    "display_name": "59",
    "probability": 0.6279,
    "tier": "Medium Risk"
  },
  {
    "supporter_id": "37",
    "display_name": "37",
    "probability": 0.6275,
    "tier": "Medium Risk"
  },
  {
    "supporter_id": "26",
    "display_name": "26",
    "probability": 0.6273,
    "tier": "Medium Risk"
  },
  {
    "supporter_id": "53",
    "display_name": "53",
    "probability": 0.6266,
    "tier": "Medium Risk"
  },
  {
    "supporter_id": "11",
    "display_name": "11",
    "probability": 0.6238,
    "tier": "Medium Risk"
  },
  {
    "supporter_id": "29",
    "display_name": "29",
    "probability": 0.623,
    "tier": "Medium Risk"
  },
  {
    "supporter_id": "12",
    "display_name": "12",
    "probability": 0.6229,
    "tier": "Medium Risk"
  },
  {
    "supporter_id": "43",
    "display_name": "43",
    "probability": 0.6228,
    "tier": "Medium Risk"
  },
  {
    "supporter_id": "34",
    "display_name": "34",
    "probability": 0.6206,
    "tier": "Medium Risk"
  },
  {
    "supporter_id": "48",
    "display_name": "48",
    "probability": 0.6152,
    "tier": "Medium Risk"
  },
  {
    "supporter_id": "11",
    "display_name": "11",
    "probability": 0.6148,
    "tier": "Medium Risk"
  },
  {
    "supporter_id": "48",
    "display_name": "48",
    "probability": 0.6137,
    "tier": "Medium Risk"
  },
  {
    "supporter_id": "37",
    "display_name": "37",
    "probability": 0.6133,
    "tier": "Medium Risk"
  },
  {
    "supporter_id": "59",
    "display_name": "59",
    "probability": 0.6116,
    "tier": "Medium Risk"
  },
  {
    "supporter_id": "50",
    "display_name": "50",
    "probability": 0.6113,
    "tier": "Medium Risk"
  },
  {
    "supporter_id": "16",
    "display_name": "16",
    "probability": 0.6108,
    "tier": "Medium Risk"
  },
  {
    "supporter_id": "21",
    "display_name": "21",
    "probability": 0.6025,
    "tier": "Medium Risk"
  },
  {
    "supporter_id": "58",
    "display_name": "58",
    "probability": 0.6024,
    "tier": "Medium Risk"
  },
  {
    "supporter_id": "5",
    "display_name": "5",
    "probability": 0.6019,
    "tier": "Medium Risk"
  },
  {
    "supporter_id": "32",
    "display_name": "32",
    "probability": 0.6005,
    "tier": "Medium Risk"
  },
  {
    "supporter_id": "39",
    "display_name": "39",
    "probability": 0.5997,
    "tier": "Medium Risk"
  },
  {
    "supporter_id": "58",
    "display_name": "58",
    "probability": 0.5982,
    "tier": "Medium Risk"
  },
  {
    "supporter_id": "47",
    "display_name": "47",
    "probability": 0.5979,
    "tier": "Medium Risk"
  },
  {
    "supporter_id": "44",
    "display_name": "44",
    "probability": 0.5963,
    "tier": "Medium Risk"
  },
  {
    "supporter_id": "12",
    "display_name": "12",
    "probability": 0.5953,
    "tier": "Medium Risk"
  },
  {
    "supporter_id": "29",
    "display_name": "29",
    "probability": 0.595,
    "tier": "Medium Risk"
  },
  {
    "supporter_id": "27",
    "display_name": "27",
    "probability": 0.5949,
    "tier": "Medium Risk"
  },
  {
    "supporter_id": "27",
    "display_name": "27",
    "probability": 0.5945,
    "tier": "Medium Risk"
  },
  {
    "supporter_id": "34",
    "display_name": "34",
    "probability": 0.5944,
    "tier": "Medium Risk"
  },
  {
    "supporter_id": "23",
    "display_name": "23",
    "probability": 0.5894,
    "tier": "Medium Risk"
  },
  {
    "supporter_id": "2",
    "display_name": "2",
    "probability": 0.5882,
    "tier": "Medium Risk"
  },
  {
    "supporter_id": "6",
    "display_name": "6",
    "probability": 0.588,
    "tier": "Medium Risk"
  },
  {
    "supporter_id": "59",
    "display_name": "59",
    "probability": 0.5868,
    "tier": "Medium Risk"
  },
  {
    "supporter_id": "43",
    "display_name": "43",
    "probability": 0.5849,
    "tier": "Medium Risk"
  },
  {
    "supporter_id": "32",
    "display_name": "32",
    "probability": 0.5848,
    "tier": "Medium Risk"
  },
  {
    "supporter_id": "43",
    "display_name": "43",
    "probability": 0.5843,
    "tier": "Medium Risk"
  },
  {
    "supporter_id": "27",
    "display_name": "27",
    "probability": 0.5839,
    "tier": "Medium Risk"
  },
  {
    "supporter_id": "39",
    "display_name": "39",
    "probability": 0.5816,
    "tier": "Medium Risk"
  },
  {
    "supporter_id": "10",
    "display_name": "10",
    "probability": 0.5806,
    "tier": "Medium Risk"
  },
  {
    "supporter_id": "2",
    "display_name": "2",
    "probability": 0.5766,
    "tier": "Medium Risk"
  },
  {
    "supporter_id": "30",
    "display_name": "30",
    "probability": 0.5757,
    "tier": "Medium Risk"
  },
  {
    "supporter_id": "18",
    "display_name": "18",
    "probability": 0.5735,
    "tier": "Medium Risk"
  },
  {
    "supporter_id": "5",
    "display_name": "5",
    "probability": 0.5696,
    "tier": "Medium Risk"
  },
  {
    "supporter_id": "45",
    "display_name": "45",
    "probability": 0.5687,
    "tier": "Medium Risk"
  },
  {
    "supporter_id": "53",
    "display_name": "53",
    "probability": 0.5644,
    "tier": "Medium Risk"
  },
  {
    "supporter_id": "49",
    "display_name": "49",
    "probability": 0.5631,
    "tier": "Medium Risk"
  },
  {
    "supporter_id": "18",
    "display_name": "18",
    "probability": 0.5628,
    "tier": "Medium Risk"
  },
  {
    "supporter_id": "9",
    "display_name": "9",
    "probability": 0.5623,
    "tier": "Medium Risk"
  },
  {
    "supporter_id": "10",
    "display_name": "10",
    "probability": 0.5617,
    "tier": "Medium Risk"
  },
  {
    "supporter_id": "18",
    "display_name": "18",
    "probability": 0.5603,
    "tier": "Medium Risk"
  },
  {
    "supporter_id": "32",
    "display_name": "32",
    "probability": 0.5593,
    "tier": "Medium Risk"
  },
  {
    "supporter_id": "39",
    "display_name": "39",
    "probability": 0.5593,
    "tier": "Medium Risk"
  },
  {
    "supporter_id": "37",
    "display_name": "37",
    "probability": 0.558,
    "tier": "Medium Risk"
  },
  {
    "supporter_id": "17",
    "display_name": "17",
    "probability": 0.5576,
    "tier": "Medium Risk"
  },
  {
    "supporter_id": "1",
    "display_name": "1",
    "probability": 0.5542,
    "tier": "Medium Risk"
  },
  {
    "supporter_id": "10",
    "display_name": "10",
    "probability": 0.5542,
    "tier": "Medium Risk"
  },
  {
    "supporter_id": "55",
    "display_name": "55",
    "probability": 0.5525,
    "tier": "Medium Risk"
  },
  {
    "supporter_id": "4",
    "display_name": "4",
    "probability": 0.5493,
    "tier": "Medium Risk"
  },
  {
    "supporter_id": "44",
    "display_name": "44",
    "probability": 0.5484,
    "tier": "Medium Risk"
  },
  {
    "supporter_id": "9",
    "display_name": "9",
    "probability": 0.5475,
    "tier": "Medium Risk"
  },
  {
    "supporter_id": "18",
    "display_name": "18",
    "probability": 0.546,
    "tier": "Medium Risk"
  },
  {
    "supporter_id": "41",
    "display_name": "41",
    "probability": 0.5457,
    "tier": "Medium Risk"
  },
  {
    "supporter_id": "13",
    "display_name": "13",
    "probability": 0.5436,
    "tier": "Medium Risk"
  },
  {
    "supporter_id": "7",
    "display_name": "7",
    "probability": 0.5434,
    "tier": "Medium Risk"
  },
  {
    "supporter_id": "32",
    "display_name": "32",
    "probability": 0.5433,
    "tier": "Medium Risk"
  },
  {
    "supporter_id": "9",
    "display_name": "9",
    "probability": 0.5423,
    "tier": "Medium Risk"
  },
  {
    "supporter_id": "19",
    "display_name": "19",
    "probability": 0.5391,
    "tier": "Medium Risk"
  },
  {
    "supporter_id": "34",
    "display_name": "34",
    "probability": 0.5369,
    "tier": "Medium Risk"
  },
  {
    "supporter_id": "52",
    "display_name": "52",
    "probability": 0.5368,
    "tier": "Medium Risk"
  },
  {
    "supporter_id": "6",
    "display_name": "6",
    "probability": 0.5343,
    "tier": "Medium Risk"
  },
  {
    "supporter_id": "23",
    "display_name": "23",
    "probability": 0.5301,
    "tier": "Medium Risk"
  },
  {
    "supporter_id": "27",
    "display_name": "27",
    "probability": 0.5285,
    "tier": "Medium Risk"
  },
  {
    "supporter_id": "33",
    "display_name": "33",
    "probability": 0.5284,
    "tier": "Medium Risk"
  },
  {
    "supporter_id": "47",
    "display_name": "47",
    "probability": 0.528,
    "tier": "Medium Risk"
  },
  {
    "supporter_id": "47",
    "display_name": "47",
    "probability": 0.5268,
    "tier": "Medium Risk"
  },
  {
    "supporter_id": "37",
    "display_name": "37",
    "probability": 0.5265,
    "tier": "Medium Risk"
  },
  {
    "supporter_id": "55",
    "display_name": "55",
    "probability": 0.5258,
    "tier": "Medium Risk"
  },
  {
    "supporter_id": "39",
    "display_name": "39",
    "probability": 0.5256,
    "tier": "Medium Risk"
  },
  {
    "supporter_id": "9",
    "display_name": "9",
    "probability": 0.5256,
    "tier": "Medium Risk"
  },
  {
    "supporter_id": "27",
    "display_name": "27",
    "probability": 0.5247,
    "tier": "Medium Risk"
  },
  {
    "supporter_id": "41",
    "display_name": "41",
    "probability": 0.5208,
    "tier": "Medium Risk"
  },
  {
    "supporter_id": "12",
    "display_name": "12",
    "probability": 0.5203,
    "tier": "Medium Risk"
  },
  {
    "supporter_id": "17",
    "display_name": "17",
    "probability": 0.5189,
    "tier": "Medium Risk"
  },
  {
    "supporter_id": "21",
    "display_name": "21",
    "probability": 0.5188,
    "tier": "Medium Risk"
  },
  {
    "supporter_id": "13",
    "display_name": "13",
    "probability": 0.5169,
    "tier": "Medium Risk"
  },
  {
    "supporter_id": "8",
    "display_name": "8",
    "probability": 0.5165,
    "tier": "Medium Risk"
  },
  {
    "supporter_id": "13",
    "display_name": "13",
    "probability": 0.5164,
    "tier": "Medium Risk"
  },
  {
    "supporter_id": "46",
    "display_name": "46",
    "probability": 0.5161,
    "tier": "Medium Risk"
  },
  {
    "supporter_id": "45",
    "display_name": "45",
    "probability": 0.5141,
    "tier": "Medium Risk"
  },
  {
    "supporter_id": "35",
    "display_name": "35",
    "probability": 0.514,
    "tier": "Medium Risk"
  },
  {
    "supporter_id": "9",
    "display_name": "9",
    "probability": 0.5137,
    "tier": "Medium Risk"
  },
  {
    "supporter_id": "6",
    "display_name": "6",
    "probability": 0.5136,
    "tier": "Medium Risk"
  },
  {
    "supporter_id": "60",
    "display_name": "60",
    "probability": 0.5123,
    "tier": "Medium Risk"
  },
  {
    "supporter_id": "29",
    "display_name": "29",
    "probability": 0.5121,
    "tier": "Medium Risk"
  },
  {
    "supporter_id": "45",
    "display_name": "45",
    "probability": 0.5089,
    "tier": "Medium Risk"
  },
  {
    "supporter_id": "46",
    "display_name": "46",
    "probability": 0.5089,
    "tier": "Medium Risk"
  },
  {
    "supporter_id": "21",
    "display_name": "21",
    "probability": 0.5088,
    "tier": "Medium Risk"
  },
  {
    "supporter_id": "13",
    "display_name": "13",
    "probability": 0.5085,
    "tier": "Medium Risk"
  },
  {
    "supporter_id": "19",
    "display_name": "19",
    "probability": 0.5084,
    "tier": "Medium Risk"
  },
  {
    "supporter_id": "3",
    "display_name": "3",
    "probability": 0.5076,
    "tier": "Medium Risk"
  },
  {
    "supporter_id": "50",
    "display_name": "50",
    "probability": 0.5068,
    "tier": "Medium Risk"
  },
  {
    "supporter_id": "47",
    "display_name": "47",
    "probability": 0.506,
    "tier": "Medium Risk"
  },
  {
    "supporter_id": "33",
    "display_name": "33",
    "probability": 0.5053,
    "tier": "Medium Risk"
  },
  {
    "supporter_id": "20",
    "display_name": "20",
    "probability": 0.503,
    "tier": "Medium Risk"
  },
  {
    "supporter_id": "60",
    "display_name": "60",
    "probability": 0.5019,
    "tier": "Medium Risk"
  },
  {
    "supporter_id": "16",
    "display_name": "16",
    "probability": 0.4999,
    "tier": "Medium Risk"
  },
  {
    "supporter_id": "21",
    "display_name": "21",
    "probability": 0.4995,
    "tier": "Medium Risk"
  },
  {
    "supporter_id": "39",
    "display_name": "39",
    "probability": 0.4991,
    "tier": "Medium Risk"
  },
  {
    "supporter_id": "16",
    "display_name": "16",
    "probability": 0.4989,
    "tier": "Medium Risk"
  },
  {
    "supporter_id": "57",
    "display_name": "57",
    "probability": 0.4984,
    "tier": "Medium Risk"
  },
  {
    "supporter_id": "4",
    "display_name": "4",
    "probability": 0.4981,
    "tier": "Medium Risk"
  },
  {
    "supporter_id": "59",
    "display_name": "59",
    "probability": 0.4971,
    "tier": "Medium Risk"
  },
  {
    "supporter_id": "20",
    "display_name": "20",
    "probability": 0.4969,
    "tier": "Medium Risk"
  },
  {
    "supporter_id": "26",
    "display_name": "26",
    "probability": 0.4959,
    "tier": "Medium Risk"
  },
  {
    "supporter_id": "19",
    "display_name": "19",
    "probability": 0.4948,
    "tier": "Medium Risk"
  },
  {
    "supporter_id": "38",
    "display_name": "38",
    "probability": 0.4937,
    "tier": "Medium Risk"
  },
  {
    "supporter_id": "44",
    "display_name": "44",
    "probability": 0.4936,
    "tier": "Medium Risk"
  },
  {
    "supporter_id": "33",
    "display_name": "33",
    "probability": 0.4934,
    "tier": "Medium Risk"
  },
  {
    "supporter_id": "6",
    "display_name": "6",
    "probability": 0.4928,
    "tier": "Medium Risk"
  },
  {
    "supporter_id": "49",
    "display_name": "49",
    "probability": 0.4917,
    "tier": "Medium Risk"
  },
  {
    "supporter_id": "17",
    "display_name": "17",
    "probability": 0.4881,
    "tier": "Medium Risk"
  },
  {
    "supporter_id": "60",
    "display_name": "60",
    "probability": 0.4873,
    "tier": "Medium Risk"
  },
  {
    "supporter_id": "7",
    "display_name": "7",
    "probability": 0.4837,
    "tier": "Medium Risk"
  },
  {
    "supporter_id": "12",
    "display_name": "12",
    "probability": 0.4837,
    "tier": "Medium Risk"
  },
  {
    "supporter_id": "60",
    "display_name": "60",
    "probability": 0.4793,
    "tier": "Medium Risk"
  },
  {
    "supporter_id": "4",
    "display_name": "4",
    "probability": 0.479,
    "tier": "Medium Risk"
  },
  {
    "supporter_id": "52",
    "display_name": "52",
    "probability": 0.4775,
    "tier": "Medium Risk"
  },
  {
    "supporter_id": "55",
    "display_name": "55",
    "probability": 0.477,
    "tier": "Medium Risk"
  },
  {
    "supporter_id": "10",
    "display_name": "10",
    "probability": 0.477,
    "tier": "Medium Risk"
  },
  {
    "supporter_id": "51",
    "display_name": "51",
    "probability": 0.4761,
    "tier": "Medium Risk"
  },
  {
    "supporter_id": "42",
    "display_name": "42",
    "probability": 0.475,
    "tier": "Medium Risk"
  },
  {
    "supporter_id": "5",
    "display_name": "5",
    "probability": 0.4724,
    "tier": "Medium Risk"
  },
  {
    "supporter_id": "25",
    "display_name": "25",
    "probability": 0.4684,
    "tier": "Medium Risk"
  },
  {
    "supporter_id": "24",
    "display_name": "24",
    "probability": 0.4683,
    "tier": "Medium Risk"
  },
  {
    "supporter_id": "34",
    "display_name": "34",
    "probability": 0.4674,
    "tier": "Medium Risk"
  },
  {
    "supporter_id": "60",
    "display_name": "60",
    "probability": 0.4661,
    "tier": "Medium Risk"
  },
  {
    "supporter_id": "6",
    "display_name": "6",
    "probability": 0.4625,
    "tier": "Medium Risk"
  },
  {
    "supporter_id": "4",
    "display_name": "4",
    "probability": 0.4596,
    "tier": "Medium Risk"
  },
  {
    "supporter_id": "4",
    "display_name": "4",
    "probability": 0.4587,
    "tier": "Medium Risk"
  },
  {
    "supporter_id": "55",
    "display_name": "55",
    "probability": 0.4586,
    "tier": "Medium Risk"
  },
  {
    "supporter_id": "6",
    "display_name": "6",
    "probability": 0.4579,
    "tier": "Medium Risk"
  },
  {
    "supporter_id": "48",
    "display_name": "48",
    "probability": 0.4577,
    "tier": "Medium Risk"
  },
  {
    "supporter_id": "26",
    "display_name": "26",
    "probability": 0.4567,
    "tier": "Medium Risk"
  },
  {
    "supporter_id": "35",
    "display_name": "35",
    "probability": 0.4527,
    "tier": "Medium Risk"
  },
  {
    "supporter_id": "19",
    "display_name": "19",
    "probability": 0.4513,
    "tier": "Medium Risk"
  },
  {
    "supporter_id": "56",
    "display_name": "56",
    "probability": 0.4472,
    "tier": "Medium Risk"
  },
  {
    "supporter_id": "38",
    "display_name": "38",
    "probability": 0.4469,
    "tier": "Medium Risk"
  },
  {
    "supporter_id": "3",
    "display_name": "3",
    "probability": 0.4435,
    "tier": "Medium Risk"
  },
  {
    "supporter_id": "36",
    "display_name": "36",
    "probability": 0.443,
    "tier": "Medium Risk"
  },
  {
    "supporter_id": "45",
    "display_name": "45",
    "probability": 0.4422,
    "tier": "Medium Risk"
  },
  {
    "supporter_id": "26",
    "display_name": "26",
    "probability": 0.4414,
    "tier": "Medium Risk"
  },
  {
    "supporter_id": "33",
    "display_name": "33",
    "probability": 0.4403,
    "tier": "Medium Risk"
  },
  {
    "supporter_id": "26",
    "display_name": "26",
    "probability": 0.4374,
    "tier": "Medium Risk"
  },
  {
    "supporter_id": "45",
    "display_name": "45",
    "probability": 0.4371,
    "tier": "Medium Risk"
  },
  {
    "supporter_id": "47",
    "display_name": "47",
    "probability": 0.4359,
    "tier": "Medium Risk"
  },
  {
    "supporter_id": "46",
    "display_name": "46",
    "probability": 0.4356,
    "tier": "Medium Risk"
  },
  {
    "supporter_id": "38",
    "display_name": "38",
    "probability": 0.4345,
    "tier": "Medium Risk"
  },
  {
    "supporter_id": "1",
    "display_name": "1",
    "probability": 0.43,
    "tier": "Medium Risk"
  },
  {
    "supporter_id": "24",
    "display_name": "24",
    "probability": 0.4289,
    "tier": "Medium Risk"
  },
  {
    "supporter_id": "5",
    "display_name": "5",
    "probability": 0.4268,
    "tier": "Medium Risk"
  },
  {
    "supporter_id": "26",
    "display_name": "26",
    "probability": 0.4255,
    "tier": "Medium Risk"
  },
  {
    "supporter_id": "24",
    "display_name": "24",
    "probability": 0.4238,
    "tier": "Medium Risk"
  },
  {
    "supporter_id": "8",
    "display_name": "8",
    "probability": 0.4232,
    "tier": "Medium Risk"
  },
  {
    "supporter_id": "45",
    "display_name": "45",
    "probability": 0.4226,
    "tier": "Medium Risk"
  },
  {
    "supporter_id": "13",
    "display_name": "13",
    "probability": 0.4195,
    "tier": "Medium Risk"
  },
  {
    "supporter_id": "34",
    "display_name": "34",
    "probability": 0.4173,
    "tier": "Medium Risk"
  },
  {
    "supporter_id": "34",
    "display_name": "34",
    "probability": 0.4129,
    "tier": "Medium Risk"
  },
  {
    "supporter_id": "34",
    "display_name": "34",
    "probability": 0.4093,
    "tier": "Medium Risk"
  },
  {
    "supporter_id": "36",
    "display_name": "36",
    "probability": 0.4065,
    "tier": "Medium Risk"
  },
  {
    "supporter_id": "52",
    "display_name": "52",
    "probability": 0.4039,
    "tier": "Medium Risk"
  },
  {
    "supporter_id": "13",
    "display_name": "13",
    "probability": 0.4028,
    "tier": "Medium Risk"
  },
  {
    "supporter_id": "24",
    "display_name": "24",
    "probability": 0.4027,
    "tier": "Medium Risk"
  },
  {
    "supporter_id": "25",
    "display_name": "25",
    "probability": 0.4025,
    "tier": "Medium Risk"
  },
  {
    "supporter_id": "35",
    "display_name": "35",
    "probability": 0.3997,
    "tier": "Low Risk"
  },
  {
    "supporter_id": "31",
    "display_name": "31",
    "probability": 0.3981,
    "tier": "Low Risk"
  },
  {
    "supporter_id": "4",
    "display_name": "4",
    "probability": 0.3951,
    "tier": "Low Risk"
  },
  {
    "supporter_id": "1",
    "display_name": "1",
    "probability": 0.3933,
    "tier": "Low Risk"
  },
  {
    "supporter_id": "7",
    "display_name": "7",
    "probability": 0.3921,
    "tier": "Low Risk"
  },
  {
    "supporter_id": "8",
    "display_name": "8",
    "probability": 0.3916,
    "tier": "Low Risk"
  },
  {
    "supporter_id": "44",
    "display_name": "44",
    "probability": 0.3865,
    "tier": "Low Risk"
  },
  {
    "supporter_id": "4",
    "display_name": "4",
    "probability": 0.385,
    "tier": "Low Risk"
  },
  {
    "supporter_id": "8",
    "display_name": "8",
    "probability": 0.384,
    "tier": "Low Risk"
  },
  {
    "supporter_id": "7",
    "display_name": "7",
    "probability": 0.3839,
    "tier": "Low Risk"
  },
  {
    "supporter_id": "26",
    "display_name": "26",
    "probability": 0.3827,
    "tier": "Low Risk"
  },
  {
    "supporter_id": "20",
    "display_name": "20",
    "probability": 0.3778,
    "tier": "Low Risk"
  },
  {
    "supporter_id": "3",
    "display_name": "3",
    "probability": 0.373,
    "tier": "Low Risk"
  },
  {
    "supporter_id": "35",
    "display_name": "35",
    "probability": 0.3711,
    "tier": "Low Risk"
  },
  {
    "supporter_id": "3",
    "display_name": "3",
    "probability": 0.3632,
    "tier": "Low Risk"
  },
  {
    "supporter_id": "7",
    "display_name": "7",
    "probability": 0.3598,
    "tier": "Low Risk"
  },
  {
    "supporter_id": "7",
    "display_name": "7",
    "probability": 0.3562,
    "tier": "Low Risk"
  },
  {
    "supporter_id": "38",
    "display_name": "38",
    "probability": 0.3539,
    "tier": "Low Risk"
  },
  {
    "supporter_id": "25",
    "display_name": "25",
    "probability": 0.3503,
    "tier": "Low Risk"
  },
  {
    "supporter_id": "20",
    "display_name": "20",
    "probability": 0.3471,
    "tier": "Low Risk"
  },
  {
    "supporter_id": "3",
    "display_name": "3",
    "probability": 0.3447,
    "tier": "Low Risk"
  },
  {
    "supporter_id": "35",
    "display_name": "35",
    "probability": 0.3445,
    "tier": "Low Risk"
  },
  {
    "supporter_id": "54",
    "display_name": "54",
    "probability": 0.3432,
    "tier": "Low Risk"
  },
  {
    "supporter_id": "25",
    "display_name": "25",
    "probability": 0.3417,
    "tier": "Low Risk"
  },
  {
    "supporter_id": "8",
    "display_name": "8",
    "probability": 0.3381,
    "tier": "Low Risk"
  },
  {
    "supporter_id": "20",
    "display_name": "20",
    "probability": 0.3347,
    "tier": "Low Risk"
  },
  {
    "supporter_id": "54",
    "display_name": "54",
    "probability": 0.3319,
    "tier": "Low Risk"
  },
  {
    "supporter_id": "38",
    "display_name": "38",
    "probability": 0.3252,
    "tier": "Low Risk"
  },
  {
    "supporter_id": "54",
    "display_name": "54",
    "probability": 0.3186,
    "tier": "Low Risk"
  },
  {
    "supporter_id": "8",
    "display_name": "8",
    "probability": 0.3153,
    "tier": "Low Risk"
  },
  {
    "supporter_id": "24",
    "display_name": "24",
    "probability": 0.3149,
    "tier": "Low Risk"
  },
  {
    "supporter_id": "31",
    "display_name": "31",
    "probability": 0.3144,
    "tier": "Low Risk"
  },
  {
    "supporter_id": "8",
    "display_name": "8",
    "probability": 0.3114,
    "tier": "Low Risk"
  },
  {
    "supporter_id": "20",
    "display_name": "20",
    "probability": 0.302,
    "tier": "Low Risk"
  },
  {
    "supporter_id": "1",
    "display_name": "1",
    "probability": 0.2979,
    "tier": "Low Risk"
  },
  {
    "supporter_id": "31",
    "display_name": "31",
    "probability": 0.2972,
    "tier": "Low Risk"
  },
  {
    "supporter_id": "35",
    "display_name": "35",
    "probability": 0.2953,
    "tier": "Low Risk"
  },
  {
    "supporter_id": "54",
    "display_name": "54",
    "probability": 0.2893,
    "tier": "Low Risk"
  },
  {
    "supporter_id": "35",
    "display_name": "35",
    "probability": 0.2844,
    "tier": "Low Risk"
  },
  {
    "supporter_id": "31",
    "display_name": "31",
    "probability": 0.2744,
    "tier": "Low Risk"
  },
  {
    "supporter_id": "31",
    "display_name": "31",
    "probability": 0.2708,
    "tier": "Low Risk"
  },
  {
    "supporter_id": "3",
    "display_name": "3",
    "probability": 0.2595,
    "tier": "Low Risk"
  },
  {
    "supporter_id": "3",
    "display_name": "3",
    "probability": 0.2548,
    "tier": "Low Risk"
  },
  {
    "supporter_id": "54",
    "display_name": "54",
    "probability": 0.2515,
    "tier": "Low Risk"
  },
  {
    "supporter_id": "31",
    "display_name": "31",
    "probability": 0.248,
    "tier": "Low Risk"
  },
  {
    "supporter_id": "25",
    "display_name": "25",
    "probability": 0.2301,
    "tier": "Low Risk"
  },
  {
    "supporter_id": "25",
    "display_name": "25",
    "probability": 0.2299,
    "tier": "Low Risk"
  },
  {
    "supporter_id": "25",
    "display_name": "25",
    "probability": 0.2208,
    "tier": "Low Risk"
  },
  {
    "supporter_id": "54",
    "display_name": "54",
    "probability": 0.2079,
    "tier": "Low Risk"
  },
  {
    "supporter_id": "54",
    "display_name": "54",
    "probability": 0.2039,
    "tier": "Low Risk"
  },
  {
    "supporter_id": "31",
    "display_name": "31",
    "probability": 0.2028,
    "tier": "Low Risk"
  },
  {
    "supporter_id": "31",
    "display_name": "31",
    "probability": 0.1957,
    "tier": "Low Risk"
  },
  {
    "supporter_id": "3",
    "display_name": "3",
    "probability": 0.1739,
    "tier": "Low Risk"
  },
  {
    "supporter_id": "25",
    "display_name": "25",
    "probability": 0.1564,
    "tier": "Low Risk"
  },
  {
    "supporter_id": "54",
    "display_name": "54",
    "probability": 0.1561,
    "tier": "Low Risk"
  }
]